bip66/__init__.py
bip66/bip66.py
bip66/tests/__init__.py
bip66/tests/test_bip66.py
test/__init__.py
test/test_bip66.py
bip66-0.4.dist-info/LICENSE
bip66-0.4.dist-info/METADATA
bip66-0.4.dist-info/WHEEL
bip66-0.4.dist-info/top_level.txt
bip66-0.4.dist-info/RECORD
