Metadata-Version: 2.1
Name: bip66
Version: 0.4
Summary: Strict DER signature encoding/decoding.
Home-page: https://github.com/KiriKiri/bip66
Author: Kirill Kirikov
Author-email: kk@4irelabs.com
License: UNKNOWN
Platform: UNKNOWN
Classifier: Programming Language :: Python :: 3
Classifier: License :: OSI Approved :: MIT License
Classifier: Operating System :: OS Independent
